pychacha/__init__.py
pychacha/classes/__init__.py
pychacha/classes/chacha.py
pychacha/classes/rsachacha.py
pychacha-1.0.3.dist-info/LICENSE
pychacha-1.0.3.dist-info/METADATA
pychacha-1.0.3.dist-info/WHEEL
pychacha-1.0.3.dist-info/top_level.txt
pychacha-1.0.3.dist-info/RECORD
