Metadata-Version: 2.1
Name: pychacha
Version: 1.0.3
Summary: ChaCha20 encryption tools for Python.
Home-page: https://github.com/thecodeforge/pychacha
Requires-Python: >=3.11
License-File: LICENSE
